Zope-5.12-py3.13-nspkg.pth
App/ApplicationManager.py
App/CacheManager.py
App/Common.py
App/DavLockManager.py
App/Dialogs.py
App/Extensions.py
App/FactoryDispatcher.py
App/FindHomes.py
App/ImageFile.py
App/Management.py
App/ProductContext.py
App/Undo.py
App/ZApplication.py
App/ZODBConnectionDebugger.py
App/__init__.py
App/config.py
App/interfaces.py
App/special_dtml.py
App/version_txt.py
App/dtml/copyright.dtml
App/dtml/cpConfiguration.dtml
App/dtml/cpContents.dtml
App/dtml/davLockManager.dtml
App/dtml/dbMain.dtml
App/dtml/debug.dtml
App/dtml/manage.dtml
App/dtml/manage_form_title.dtml
App/dtml/manage_navbar.dtml
App/dtml/manage_page_footer.dtml
App/dtml/manage_page_header.dtml
App/dtml/manage_tabs.dtml
App/dtml/menu.dtml
App/dtml/undo.dtml
App/dtml/zodbConnections.dtml
App/tests/__init__.py
App/tests/testImageFile.py
App/tests/testManagement.py
App/tests/test_ApplicationManager.py
App/tests/test_Dialogs.py
App/tests/test_Extensions.py
App/tests/test_ProductContext.py
App/tests/test_cachemanager.py
App/tests/test_class_init.py
App/tests/test_getZopeVersion.py
App/tests/test_setConfiguration.py
App/tests/fixtures/error.py
App/tests/fixtures/getObject.py
App/www/chooseDatabase.pt
App/www/zopelogo.png
OFS/Application.py
OFS/Cache.py
OFS/CopySupport.py
OFS/DTMLDocument.py
OFS/DTMLMethod.py
OFS/EtagSupport.py
OFS/FindSupport.py
OFS/Folder.py
OFS/History.py
OFS/Image.py
OFS/LockItem.py
OFS/Lockable.py
OFS/Moniker.py
OFS/ObjectManager.py
OFS/OrderSupport.py
OFS/OrderedFolder.py
OFS/PropertyManager.py
OFS/PropertySheets.py
OFS/SimpleItem.py
OFS/Traversable.py
OFS/Uninstalled.py
OFS/__init__.py
OFS/absoluteurl.py
OFS/absoluteurl.zcml
OFS/configure.zcml
OFS/deprecated.zcml
OFS/event.py
OFS/event.txt
OFS/event.zcml
OFS/interfaces.py
OFS/meta.zcml
OFS/metaconfigure.py
OFS/metadirectives.py
OFS/misc_.py
OFS/owner.py
OFS/role.py
OFS/subscribers.py
OFS/userfolder.py
OFS/browser/__init__.py
OFS/browser/configure.zcml
OFS/dtml/access.dtml
OFS/dtml/acquiredEdit.dtml
Zope-5.12.dist-info/LICENSE.txt
Zope-5.12.dist-info/METADATA
Zope-5.12.dist-info/WHEEL
Zope-5.12.dist-info/entry_points.txt
Zope-5.12.dist-info/namespace_packages.txt
Zope-5.12.dist-info/top_level.txt
Zope-5.12.dist-info/RECORD
