Metadata-Version: 2.1
Name: Zope
Version: 5.12
Summary: Zope application server / web framework
Home-page: https://zope.readthedocs.io/en/latest/
Author: Zope Foundation and Contributors
Author-email: zope-dev@zope.dev
License: ZPL 2.1
Project-URL: Documentation, https://zope.readthedocs.io
Project-URL: Issue Tracker, https://github.com/zopefoundation/Zope/issues
Project-URL: Sources, https://github.com/zopefoundation/Zope
Classifier: Development Status :: 6 - Mature
Classifier: Environment :: Web Environment
Classifier: Framework :: Zope :: 5
Classifier: Intended Audience :: Developers
Classifier: License :: OSI Approved :: Zope Public License
Classifier: Operating System :: OS Independent
Classifier: Programming Language :: Python :: 3
Classifier: Programming Language :: Python :: 3.8
Classifier: Programming Language :: Python :: 3.9
Classifier: Programming Language :: Python :: 3.10
Classifier: Programming Language :: Python :: 3.11
Classifier: Programming Language :: Python :: 3.12
Classifier: Programming Language :: Python :: 3.13
Classifier: Programming Language :: Python :: Implementation :: CPython
Classifier: Topic :: Internet :: WWW/HTTP :: Dynamic Content
Classifier: Topic :: Internet :: WWW/HTTP :: WSGI :: Application
Classifier: Topic :: Software Development :: Libraries :: Application Frameworks
Requires-Python: >= 3.8
License-File: LICENSE.txt
Requires-Dist: AccessControl>=5.2
Requires-Dist: Acquisition
Requires-Dist: BTrees
Requires-Dist: Chameleon>=3.7.0
Requires-Dist: DateTime
Requires-Dist: DocumentTemplate>=4.0
Requires-Dist: ExtensionClass
Requires-Dist: MultiMapping
Requires-Dist: PasteDeploy
Requires-Dist: Persistence
Requires-Dist: RestrictedPython
Requires-Dist: ZConfig>=2.9.2
Requires-Dist: ZODB
Requires-Dist: setuptools>=36.2
Requires-Dist: transaction>=2.4
Requires-Dist: waitress
Requires-Dist: zExceptions>=3.4
Requires-Dist: z3c.pt
Requires-Dist: zope.browser
Requires-Dist: zope.browsermenu
Requires-Dist: zope.browserpage>=4.4.0.dev0
Requires-Dist: zope.browserresource>=3.11
Requires-Dist: zope.component
Requires-Dist: zope.configuration
Requires-Dist: zope.container
Requires-Dist: zope.contentprovider
Requires-Dist: zope.contenttype
Requires-Dist: zope.datetime
Requires-Dist: zope.deferredimport
Requires-Dist: zope.event
Requires-Dist: zope.exceptions
Requires-Dist: zope.globalrequest
Requires-Dist: zope.i18n[zcml]
Requires-Dist: zope.i18nmessageid
Requires-Dist: zope.interface>=3.8
Requires-Dist: zope.lifecycleevent
Requires-Dist: zope.location
Requires-Dist: zope.pagetemplate>=4.0.2
Requires-Dist: zope.processlifetime
Requires-Dist: zope.proxy
Requires-Dist: zope.ptresource
Requires-Dist: zope.publisher
Requires-Dist: zope.schema
Requires-Dist: zope.security
Requires-Dist: zope.sequencesort
Requires-Dist: zope.site
Requires-Dist: zope.size
Requires-Dist: zope.tal
Requires-Dist: zope.tales>=5.0.2
Requires-Dist: zope.testbrowser
Requires-Dist: zope.testing
Requires-Dist: zope.traversing
Requires-Dist: zope.viewlet
Requires-Dist: multipart
Provides-Extra: docs
Requires-Dist: Sphinx; extra == "docs"
Requires-Dist: furo; extra == "docs"
Requires-Dist: tempstorage; extra == "docs"
Provides-Extra: wsgi
Requires-Dist: Paste; extra == "wsgi"
